prisma_tui-0.2.0.dist-info/licenses/LICENSE
prismatui/__init__.py
prismatui/_tui/__init__.py
prismatui/_tui/_backend/__init__.py
prismatui/_tui/_backend/backend.py
prismatui/_tui/_backend/backend_curses.py
prismatui/_tui/_backend/constants.py
prismatui/_tui/_components/__init__.py
prismatui/_tui/_components/layer.py
prismatui/_tui/_components/pixel.py
prismatui/_tui/_components/section.py
prismatui/_tui/_components/terminal.py
prismatui/_tui/_misc/__init__.py
prismatui/_tui/_misc/blend_mode.py
prismatui/_tui/_misc/palette.py
prismatui/_tui/_misc/parser_pri.py
prismatui/_utils/__init__.py
prismatui/_utils/debug_logger.py
prismatui/_utils/mosaic_parser.py
prisma_tui-0.2.0.dist-info/METADATA
prisma_tui-0.2.0.dist-info/WHEEL
prisma_tui-0.2.0.dist-info/top_level.txt
prisma_tui-0.2.0.dist-info/RECORD
